LICENSE
README.md
setup.cfg
setup.py
lasertools_pulsedispersiondata/__init__.py
lasertools_pulsedispersiondata/helpers.py
lasertools_pulsedispersiondata/loader.py
lasertools_pulsedispersiondata.egg-info/PKG-INFO
lasertools_pulsedispersiondata.egg-info/SOURCES.txt
lasertools_pulsedispersiondata.egg-info/dependency_links.txt
lasertools_pulsedispersiondata.egg-info/requires.txt
lasertools_pulsedispersiondata.egg-info/top_level.txt
lasertools_pulsedispersiondata/arbitrary_index/KBr.json
lasertools_pulsedispersiondata/arbitrary_index/air.json
lasertools_pulsedispersiondata/arbitrary_phase/gratings.json
lasertools_pulsedispersiondata/arbitrary_phase/polynomial.json
lasertools_pulsedispersiondata/numerical_gdd/Layertec_182697_p.json
lasertools_pulsedispersiondata/numerical_gdd/Layertec_182697_s.json
lasertools_pulsedispersiondata/numerical_gdd/UFI_HD120_u.json
lasertools_pulsedispersiondata/numerical_gdd/UFI_HD2203_u.json
lasertools_pulsedispersiondata/numerical_gdd/UFI_HD59_p.json
lasertools_pulsedispersiondata/numerical_gdd/bain_custom_1_rs.json
lasertools_pulsedispersiondata/numerical_gdd/bain_custom_1_tp.json
lasertools_pulsedispersiondata/numerical_gdd/bain_custom_1_ts.json
lasertools_pulsedispersiondata/numerical_phase/UFI_HD120_u_alt.json
lasertools_pulsedispersiondata/numerical_phase/UFI_HD2203_u_alt.json
lasertools_pulsedispersiondata/sellmeier_index/BK7.json
lasertools_pulsedispersiondata/sellmeier_index/CaF2.json
lasertools_pulsedispersiondata/sellmeier_index/FS.json
lasertools_pulsedispersiondata/sellmeier_index/MgF2.json
lasertools_pulsedispersiondata/sellmeier_index/Si.json
lasertools_pulsedispersiondata/sellmeier_index/ZnSe.json